{
  "license_title": null,
  "maintainer": null,
  "relationships_as_object": [

  ],
  "private": false,
  "maintainer_email": null,
  "num_tags": 0,
  "id": "c687851a-33f3-4159-8c44-35918ca7d8a3",
  "metadata_created": "2016-01-30T06:45:24.247378",
  "metadata_modified": "2016-02-22T22:44:19.593672",
  "author": null,
  "author_email": null,
  "state": "active",
  "version": null,
  "creator_user_id": "47303a9e-1187-4290-85a3-1fc02dc49e4a",
  "type": "dataset",
  "resources": [
    {
      "cache_last_updated": null,
      "package_id": "c687851a-33f3-4159-8c44-35918ca7d8a3",
      "webstore_last_updated": null,
      "id": "4c0afed8-86dd-4642-b757-7f6d27522eea",
      "size": null,
      "state": "active",
      "resource_locator_function": "search",
      "hash": "",
      "description": "Interactive map viewer to allow discovery and access to water column sonar data",
      "format": "Simrad EK500 data logged with BI500 system",
      "tracking_summary": {
        "total": 2122,
        "recent": 42
      },
      "mimetype_inner": null,
      "url_type": null,
      "resource_locator_protocol": "",
      "mimetype": null,
      "cache_url": null,
      "name": "Water Column Sonar Data Map Viewer",
      "created": "2016-02-22T17:44:19.762744",
      "url": "http://maps.ngdc.noaa.gov/viewers/water_column_sonar/",
      "webstore_url": null,
      "last_modified": null,
      "position": 0,
      "revision_id": "917382a0-f8fb-49fc-891d-bc11ef323208",
      "resource_type": null
    },
    {
      "cache_last_updated": null,
      "package_id": "c687851a-33f3-4159-8c44-35918ca7d8a3",
      "webstore_last_updated": null,
      "id": "b34cbedf-53c3-479d-968e-fa4868bf3522",
      "size": null,
      "state": "active",
      "resource_locator_function": "information",
      "hash": "",
      "description": "Have a Comment for the GCMD?",
      "format": "",
      "tracking_summary": {
        "total": 425,
        "recent": 22
      },
      "mimetype_inner": null,
      "url_type": null,
      "resource_locator_protocol": "",
      "mimetype": null,
      "cache_url": null,
      "name": "GCMD Feedback Form",
      "created": "2016-02-22T17:44:19.762782",
      "url": "http://gcmd.nasa.gov/MailComments/MailComments.jsf?rcpt=gcmduso",
      "webstore_url": null,
      "last_modified": null,
      "position": 1,
      "revision_id": "917382a0-f8fb-49fc-891d-bc11ef323208",
      "resource_type": null
    },
    {
      "cache_last_updated": null,
      "package_id": "c687851a-33f3-4159-8c44-35918ca7d8a3",
      "webstore_last_updated": null,
      "id": "c330b704-b27e-4caa-8665-5ec184205ef3",
      "size": null,
      "state": "active",
      "resource_locator_function": "information",
      "hash": "",
      "description": "This page describes the NASA GCMD Keywords, how to reference those keywords and provides download instructions.",
      "format": "HTML",
      "tracking_summary": {
        "total": 486,
        "recent": 12
      },
      "mimetype_inner": null,
      "url_type": null,
      "resource_locator_protocol": "",
      "mimetype": null,
      "cache_url": null,
      "name": "GCMD's Science Keywords and Associated Directory Keywords",
      "created": "2016-02-22T17:44:19.762793",
      "url": "http://gcmd.nasa.gov/learn/keyword_list.html",
      "webstore_url": null,
      "last_modified": null,
      "position": 2,
      "revision_id": "917382a0-f8fb-49fc-891d-bc11ef323208",
      "resource_type": null
    },
    {
      "cache_last_updated": null,
      "package_id": "c687851a-33f3-4159-8c44-35918ca7d8a3",
      "webstore_last_updated": null,
      "id": "eee84bd8-c8c6-4b04-8a9b-a61a2d56ffe4",
      "size": null,
      "state": "active",
      "resource_locator_function": "information",
      "hash": "",
      "description": "Publication of Sea Areas is maintained by IHO.",
      "format": "PDF",
      "tracking_summary": {
        "total": 8,
        "recent": 2
      },
      "mimetype_inner": null,
      "url_type": null,
      "resource_locator_protocol": "",
      "mimetype": null,
      "cache_url": null,
      "name": "International Hydrographic Organization (IHO) Sea Area (\"Limits of Oceans and Seas\" publication S-23)",
      "created": "2016-02-22T17:44:19.762801",
      "url": "http://www.iho-ohi.net/iho_pubs/standard/S-23/S23_1953.pdf",
      "webstore_url": null,
      "last_modified": null,
      "position": 3,
      "revision_id": "917382a0-f8fb-49fc-891d-bc11ef323208",
      "resource_type": null
    },
    {
      "cache_last_updated": null,
      "package_id": "c687851a-33f3-4159-8c44-35918ca7d8a3",
      "webstore_last_updated": null,
      "id": "b12a1644-f00f-445b-9e08-183f32760e10",
      "size": null,
      "state": "active",
      "resource_locator_function": "information",
      "hash": "",
      "description": "Have a Comment for the GCMD?",
      "format": "",
      "tracking_summary": {
        "total": 425,
        "recent": 22
      },
      "mimetype_inner": null,
      "url_type": null,
      "resource_locator_protocol": "",
      "mimetype": null,
      "cache_url": null,
      "name": "GCMD Feedback Form",
      "created": "2016-02-22T17:44:19.762808",
      "url": "http://gcmd.nasa.gov/MailComments/MailComments.jsf?rcpt=gcmduso",
      "webstore_url": null,
      "last_modified": null,
      "position": 4,
      "revision_id": "917382a0-f8fb-49fc-891d-bc11ef323208",
      "resource_type": null
    },
    {
      "cache_last_updated": null,
      "package_id": "c687851a-33f3-4159-8c44-35918ca7d8a3",
      "webstore_last_updated": null,
      "id": "09f47ac6-853f-4f44-9274-c41eeec790f7",
      "size": null,
      "state": "active",
      "resource_locator_function": "information",
      "hash": "",
      "description": "This page describes the NASA GCMD Keywords, how to reference those keywords and provides download instructions.",
      "format": "HTML",
      "tracking_summary": {
        "total": 486,
        "recent": 12
      },
      "mimetype_inner": null,
      "url_type": null,
      "resource_locator_protocol": "",
      "mimetype": null,
      "cache_url": null,
      "name": "GCMD's Science Keywords and Associated Directory Keywords",
      "created": "2016-02-22T17:44:19.762815",
      "url": "http://gcmd.nasa.gov/learn/keyword_list.html",
      "webstore_url": null,
      "last_modified": null,
      "position": 5,
      "revision_id": "917382a0-f8fb-49fc-891d-bc11ef323208",
      "resource_type": null
    },
    {
      "cache_last_updated": null,
      "package_id": "c687851a-33f3-4159-8c44-35918ca7d8a3",
      "webstore_last_updated": null,
      "id": "30ceca70-8da6-4943-ac17-a6dcf8382dc3",
      "size": null,
      "state": "active",
      "resource_locator_function": "information",
      "hash": "",
      "description": "Have a Comment for the GCMD?",
      "format": "",
      "tracking_summary": {
        "total": 425,
        "recent": 22
      },
      "mimetype_inner": null,
      "url_type": null,
      "resource_locator_protocol": "",
      "mimetype": null,
      "cache_url": null,
      "name": "GCMD Feedback Form",
      "created": "2016-02-22T17:44:19.762823",
      "url": "http://gcmd.nasa.gov/MailComments/MailComments.jsf?rcpt=gcmduso",
      "webstore_url": null,
      "last_modified": null,
      "position": 6,
      "revision_id": "917382a0-f8fb-49fc-891d-bc11ef323208",
      "resource_type": null
    },
    {
      "cache_last_updated": null,
      "package_id": "c687851a-33f3-4159-8c44-35918ca7d8a3",
      "webstore_last_updated": null,
      "id": "9124dc79-d298-4f8d-b8a4-4e86590c5a26",
      "size": null,
      "state": "active",
      "resource_locator_function": "information",
      "hash": "",
      "description": "This page describes the NASA GCMD Keywords, how to reference those keywords and provides download instructions.",
      "format": "HTML",
      "tracking_summary": {
        "total": 486,
        "recent": 12
      },
      "mimetype_inner": null,
      "url_type": null,
      "resource_locator_protocol": "",
      "mimetype": null,
      "cache_url": null,
      "name": "GCMD's Science Keywords and Associated Directory Keywords",
      "created": "2016-02-22T17:44:19.762830",
      "url": "http://gcmd.nasa.gov/learn/keyword_list.html",
      "webstore_url": null,
      "last_modified": null,
      "position": 7,
      "revision_id": "917382a0-f8fb-49fc-891d-bc11ef323208",
      "resource_type": null
    },
    {
      "cache_last_updated": null,
      "package_id": "c687851a-33f3-4159-8c44-35918ca7d8a3",
      "webstore_last_updated": null,
      "id": "4ed9b33b-1c26-4df2-9290-c0c09145b9b5",
      "size": null,
      "state": "active",
      "resource_locator_function": "information",
      "hash": "",
      "description": "Have a Comment for the GCMD?",
      "format": "",
      "tracking_summary": {
        "total": 425,
        "recent": 22
      },
      "mimetype_inner": null,
      "url_type": null,
      "resource_locator_protocol": "",
      "mimetype": null,
      "cache_url": null,
      "name": "GCMD Feedback Form",
      "created": "2016-02-22T17:44:19.762837",
      "url": "http://gcmd.nasa.gov/MailComments/MailComments.jsf?rcpt=gcmduso",
      "webstore_url": null,
      "last_modified": null,
      "position": 8,
      "revision_id": "917382a0-f8fb-49fc-891d-bc11ef323208",
      "resource_type": null
    },
    {
      "cache_last_updated": null,
      "package_id": "c687851a-33f3-4159-8c44-35918ca7d8a3",
      "webstore_last_updated": null,
      "id": "7fd88f70-51f1-4a6c-8059-7b0c0e7f0971",
      "size": null,
      "state": "active",
      "resource_locator_function": "information",
      "hash": "",
      "description": "This page describes the NASA GCMD Keywords, how to reference those keywords and provides download instructions.",
      "format": "HTML",
      "tracking_summary": {
        "total": 486,
        "recent": 12
      },
      "mimetype_inner": null,
      "url_type": null,
      "resource_locator_protocol": "",
      "mimetype": null,
      "cache_url": null,
      "name": "GCMD's Science Keywords and Associated Directory Keywords",
      "created": "2016-02-22T17:44:19.762844",
      "url": "http://gcmd.nasa.gov/learn/keyword_list.html",
      "webstore_url": null,
      "last_modified": null,
      "position": 9,
      "revision_id": "917382a0-f8fb-49fc-891d-bc11ef323208",
      "resource_type": null
    }
  ],
  "num_resources": 10,
  "tags": [

  ],
  "tracking_summary": {
    "total": 1,
    "recent": 1
  },
  "groups": [

  ],
  "license_id": null,
  "relationships_as_subject": [

  ],
  "organization": {
    "description": "",
    "created": "2013-03-14T03:44:40.434269",
    "title": "National Oceanic and Atmospheric Administration, Department of Commerce",
    "name": "noaa-gov",
    "is_organization": true,
    "state": "active",
    "image_url": "https://fortress.wa.gov/dfw/score/score/images/noaa_logo.png",
    "revision_id": "c6d43080-22e1-405e-a83d-f2a512d9e867",
    "type": "organization",
    "id": "e811f0b4-451f-4896-9e8f-fc6802837819",
    "approval_status": "approved"
  },
  "name": "nefsc-1999-spring-bottom-trawl-survey-al9903",
  "isopen": false,
  "url": null,
  "notes": "The objectives of the cruise are to: (1) determine the spring distribution and relative abundance of fish and selected invertebrate species; (2) collect biological samples for studies of age and growth relationships, fecundity, maturity and food habits; (3) collect hydrographic and meteorological data; (4)\ncollect samples of ichthyoplankton and zooplankton; and (5) make data and sample collections for cooperative researchers and programs; (6) conduct a hydroacoustic survey between survey stations.",
  "owner_org": "e811f0b4-451f-4896-9e8f-fc6802837819",
  "extras": [
    {
      "key": "bbox-east-long",
      "value": "-65.72054"
    },
    {
      "key": "resource-type",
      "value": "series"
    },
    {
      "key": "bbox-north-lat",
      "value": "44.34813"
    },
    {
      "key": "coupled-resource",
      "value": "[]"
    },
    {
      "key": "guid",
      "value": "gov.noaa.ngdc.mgg.wcd:AL9903_EK500"
    },
    {
      "key": "spatial_harvester",
      "value": true
    },
    {
      "key": "bbox-south-lat",
      "value": "34.4779"
    },
    {
      "key": "spatial-reference-system",
      "value": "urn:ogc:def:crs:EPSG:4326"
    },
    {
      "key": "spatial",
      "value": "{\"type\": \"Polygon\", \"coordinates\": [[[-75.89826, 34.4779], [-65.72054, 34.4779], [-65.72054, 44.34813], [-75.89826, 44.34813], [-75.89826, 34.4779]]]}"
    },
    {
      "key": "progress",
      "value": "completed"
    },
    {
      "key": "access_constraints",
      "value": "[\"Cite as: Northeast Fisheries Science Center (1999): Water Column Sonar Data Collection (AL9903, EK500). National Centers for Environmental Information, NOAA. doi:10.7289/V5CV4FQF [access date]\", \"Resource may not be available for up to one year after initial collection.\"]"
    },
    {
      "key": "temporal-extent-begin",
      "value": "1999-03-01T22:05:34"
    },
    {
      "key": "contact-email",
      "value": "john.galbraith@noaa.gov"
    },
    {
      "key": "bbox-west-long",
      "value": "-75.89826"
    },
    {
      "key": "metadata-date",
      "value": "2016-01-26"
    },
    {
      "key": "dataset-reference-date",
      "value": "[{\"type\": \"creation\", \"value\": \"1999-03-01\"}]"
    },
    {
      "key": "frequency-of-update",
      "value": "notPlanned"
    },
    {
      "key": "licence",
      "value": "[\"While every effort has been made to ensure that these data are accurate and reliable within the limits of the current state of the art, NOAA cannot assume liability for any damages caused by any errors or omissions in the data, nor as a result of the failure of the data to function on a particular system. NOAA makes no warranty, expressed or implied, nor does the fact of distribution constitute such a warranty.\", \"These data are considered raw and have not been subjected to the NOAA's quality control or quality assurance procedures. They are released for limited public use as preliminary data to be used only with appropriate caution. NOAA cannot assume liability for any damages caused by any errors or omissions in the data, nor as a result of the failure of the data to function on a particular system. NOAA makes no warranty, expressed or implied, nor does the fact of distribution constitute such a warranty.\", \"Not subject to copyright protection within the United States.\"]"
    },
    {
      "key": "metadata_type",
      "value": "geospatial"
    },
    {
      "key": "responsible-party",
      "value": "[{\"name\": \"NEFSC\", \"roles\": [\"principalInvestigator\"]}]"
    },
    {
      "key": "temporal-extent-end",
      "value": "1999-04-22T23:26:11"
    },
    {
      "key": "spatial-data-service-type",
      "value": ""
    },
    {
      "key": "metadata-language",
      "value": ""
    },
    {
      "key": "tags",
      "value": "wcms, global, doc/noaa/nesdis/ncei, earth science, aquatic ecosystems, vertical location, profilers/sounders, in situ/laboratory instruments, aquatic sciences, sea floor, benthic habitat, doc/noaa/nmfs, north atlantic ocean, seafloor topography, national centers for environmental information, nesdis, noaa, u.s. department of commerce, acoustic sounders, marine habitat, oceans, fisheries, bathymetry, acoustic scattering, national marine fisheries service, noaa, u.s. department of commerce, ocean acoustics, doc/noaa/nesdis/ngdc, water column mapping system, biosphere, pelagic habitat, bathymetry/seafloor topography, national geophysical data center, nesdis, noaa, u.s. department of commerce"
    },
    {
      "key": "harvest_object_id",
      "value": "f8156d1f-01a9-488f-ae52-3bfec34e021f"
    },
    {
      "key": "harvest_source_id",
      "value": "2aed8e29-fc5b-4cde-aa66-fb1118fd705e"
    },
    {
      "key": "harvest_source_title",
      "value": "NOAA CSW Harvest Source"
    }
  ],
  "title": "NEFSC 1999 Spring Bottom Trawl Survey (AL9903, EK500)",
  "revision_id": "917382a0-f8fb-49fc-891d-bc11ef323208"
}