{
  "license_title": null,
  "maintainer": null,
  "relationships_as_object": [

  ],
  "private": false,
  "maintainer_email": null,
  "num_tags": 0,
  "id": "bcff92d0-b503-4d02-a119-5aabc1efcf58",
  "metadata_created": "2015-09-27T00:00:05.312664",
  "metadata_modified": "2016-10-04T02:14:33.828301",
  "author": null,
  "author_email": null,
  "state": "active",
  "version": null,
  "creator_user_id": "47303a9e-1187-4290-85a3-1fc02dc49e4a",
  "type": "dataset",
  "resources": [
    {
      "cache_last_updated": null,
      "package_id": "bcff92d0-b503-4d02-a119-5aabc1efcf58",
      "webstore_last_updated": null,
      "id": "1a9d3d9c-5842-4aeb-b451-c1bba5a299a7",
      "size": null,
      "state": "active",
      "resource_locator_function": "information",
      "hash": "",
      "description": "Navigate directly to the URL for a descriptive web page with download links.",
      "format": "Originator data format",
      "tracking_summary": {
        "total": 0,
        "recent": 0
      },
      "mimetype_inner": null,
      "url_type": null,
      "resource_locator_protocol": "HTTP",
      "mimetype": null,
      "cache_url": null,
      "name": "Descriptive Information",
      "created": "2016-10-03T22:14:34.212633",
      "url": "https://accession.nodc.noaa.gov/8100587",
      "webstore_url": null,
      "last_modified": null,
      "position": 0,
      "revision_id": "5ec3b6be-d505-43e9-ae8a-9d7b6716f5a8",
      "resource_type": null
    },
    {
      "cache_last_updated": null,
      "package_id": "bcff92d0-b503-4d02-a119-5aabc1efcf58",
      "webstore_last_updated": null,
      "id": "7d5bc437-43d7-4a39-9f38-2ce759d18936",
      "size": null,
      "state": "active",
      "resource_locator_function": "information",
      "hash": "",
      "description": "Navigate directly to the URL for a descriptive web page with download links.",
      "format": "Originator data format",
      "tracking_summary": {
        "total": 0,
        "recent": 0
      },
      "mimetype_inner": null,
      "url_type": null,
      "resource_locator_protocol": "HTTP",
      "mimetype": null,
      "cache_url": null,
      "name": "Descriptive Information",
      "created": "2016-10-03T22:14:34.212656",
      "url": "https://accession.nodc.noaa.gov/oas/8100587",
      "webstore_url": null,
      "last_modified": null,
      "position": 1,
      "revision_id": "5ec3b6be-d505-43e9-ae8a-9d7b6716f5a8",
      "resource_type": null
    },
    {
      "cache_last_updated": null,
      "package_id": "bcff92d0-b503-4d02-a119-5aabc1efcf58",
      "webstore_last_updated": null,
      "id": "6d55cad9-fec0-46fd-84ab-90f6ccd02d3f",
      "size": null,
      "state": "active",
      "resource_locator_function": "download",
      "hash": "",
      "description": "Navigate directly to the URL for data access and direct download.",
      "format": "Originator data format",
      "tracking_summary": {
        "total": 0,
        "recent": 0
      },
      "mimetype_inner": null,
      "url_type": null,
      "resource_locator_protocol": "HTTP",
      "mimetype": null,
      "cache_url": null,
      "name": "HTTP",
      "created": "2016-10-03T22:14:34.212665",
      "url": "https://accession.nodc.noaa.gov/download/8100587",
      "webstore_url": null,
      "last_modified": null,
      "position": 2,
      "revision_id": "5ec3b6be-d505-43e9-ae8a-9d7b6716f5a8",
      "resource_type": null
    },
    {
      "cache_last_updated": null,
      "package_id": "bcff92d0-b503-4d02-a119-5aabc1efcf58",
      "webstore_last_updated": null,
      "id": "457f0d3c-e15b-426e-b4ab-fbd7e6acbff8",
      "size": null,
      "state": "active",
      "resource_locator_function": "download",
      "hash": "",
      "description": "These data are available through the File Transfer Protocol (FTP). You may use any FTP client to download these data.",
      "format": "Originator data format",
      "tracking_summary": {
        "total": 0,
        "recent": 0
      },
      "mimetype_inner": null,
      "url_type": null,
      "resource_locator_protocol": "FTP",
      "mimetype": null,
      "cache_url": null,
      "name": "FTP",
      "created": "2016-10-03T22:14:34.212673",
      "url": "ftp://ftp.nodc.noaa.gov/nodc/archive/arc0001/8100587/",
      "webstore_url": null,
      "last_modified": null,
      "position": 3,
      "revision_id": "5ec3b6be-d505-43e9-ae8a-9d7b6716f5a8",
      "resource_type": null
    },
    {
      "cache_last_updated": null,
      "package_id": "bcff92d0-b503-4d02-a119-5aabc1efcf58",
      "webstore_last_updated": null,
      "id": "fc234ebb-751a-4c63-b3d2-3431e01e6361",
      "size": null,
      "state": "active",
      "resource_locator_function": "information",
      "hash": "",
      "description": "Main NCEI website providing links to access data and data services.",
      "format": "",
      "tracking_summary": {
        "total": 51,
        "recent": 8
      },
      "mimetype_inner": null,
      "url_type": null,
      "resource_locator_protocol": "HTTP",
      "mimetype": null,
      "cache_url": null,
      "name": "NOAA National Centers for Environmental Information website",
      "created": "2016-10-03T22:14:34.212681",
      "url": "https://www.ncei.noaa.gov/",
      "webstore_url": null,
      "last_modified": null,
      "position": 4,
      "revision_id": "5ec3b6be-d505-43e9-ae8a-9d7b6716f5a8",
      "resource_type": null
    },
    {
      "cache_last_updated": null,
      "package_id": "bcff92d0-b503-4d02-a119-5aabc1efcf58",
      "webstore_last_updated": null,
      "id": "6323a9ad-f7c1-4b27-b717-a8d11de6717b",
      "size": null,
      "state": "active",
      "resource_locator_function": "information",
      "hash": "",
      "description": "Main NODC website providing links to access data and data services.",
      "format": "",
      "tracking_summary": {
        "total": 7,
        "recent": 1
      },
      "mimetype_inner": null,
      "url_type": null,
      "resource_locator_protocol": "HTTP",
      "mimetype": null,
      "cache_url": null,
      "name": "NOAA National Oceanographic Data Center website",
      "created": "2016-10-03T22:14:34.212688",
      "url": "https://www.nodc.noaa.gov/",
      "webstore_url": null,
      "last_modified": null,
      "position": 5,
      "revision_id": "5ec3b6be-d505-43e9-ae8a-9d7b6716f5a8",
      "resource_type": null
    },
    {
      "cache_last_updated": null,
      "package_id": "bcff92d0-b503-4d02-a119-5aabc1efcf58",
      "webstore_last_updated": null,
      "id": "d5335a02-7a44-49ad-b2c8-28ab237bbe82",
      "size": null,
      "state": "active",
      "resource_locator_function": "information",
      "hash": "",
      "description": "Main NCEI website providing links to access data and data services.",
      "format": "",
      "tracking_summary": {
        "total": 51,
        "recent": 8
      },
      "mimetype_inner": null,
      "url_type": null,
      "resource_locator_protocol": "HTTP",
      "mimetype": null,
      "cache_url": null,
      "name": "NOAA National Centers for Environmental Information website",
      "created": "2016-10-03T22:14:34.212696",
      "url": "https://www.ncei.noaa.gov/",
      "webstore_url": null,
      "last_modified": null,
      "position": 6,
      "revision_id": "5ec3b6be-d505-43e9-ae8a-9d7b6716f5a8",
      "resource_type": null
    },
    {
      "cache_last_updated": null,
      "package_id": "bcff92d0-b503-4d02-a119-5aabc1efcf58",
      "webstore_last_updated": null,
      "id": "6f631478-cc60-4e60-93fa-f2bb9027cc07",
      "size": null,
      "state": "active",
      "resource_locator_function": "information",
      "hash": "",
      "description": "Overview of the NASA GCMD Keywords.",
      "format": "HTML",
      "tracking_summary": {
        "total": 163,
        "recent": 14
      },
      "mimetype_inner": null,
      "url_type": null,
      "resource_locator_protocol": "HTTP",
      "mimetype": null,
      "cache_url": null,
      "name": "NASA GCMD Keyword Community Page",
      "created": "2016-10-03T22:14:34.212703",
      "url": "http://gcmd.gsfc.nasa.gov/learn/keywords.html",
      "webstore_url": null,
      "last_modified": null,
      "position": 7,
      "revision_id": "5ec3b6be-d505-43e9-ae8a-9d7b6716f5a8",
      "resource_type": null
    },
    {
      "cache_last_updated": null,
      "package_id": "bcff92d0-b503-4d02-a119-5aabc1efcf58",
      "webstore_last_updated": null,
      "id": "85130ed6-8e24-48ef-bca8-b24047d51cc3",
      "size": null,
      "state": "active",
      "resource_locator_function": "information",
      "hash": "",
      "description": "Overview of the NASA GCMD Keywords.",
      "format": "HTML",
      "tracking_summary": {
        "total": 163,
        "recent": 14
      },
      "mimetype_inner": null,
      "url_type": null,
      "resource_locator_protocol": "HTTP",
      "mimetype": null,
      "cache_url": null,
      "name": "NASA GCMD Keyword Community Page",
      "created": "2016-10-03T22:14:34.212710",
      "url": "http://gcmd.gsfc.nasa.gov/learn/keywords.html",
      "webstore_url": null,
      "last_modified": null,
      "position": 8,
      "revision_id": "5ec3b6be-d505-43e9-ae8a-9d7b6716f5a8",
      "resource_type": null
    },
    {
      "cache_last_updated": null,
      "package_id": "bcff92d0-b503-4d02-a119-5aabc1efcf58",
      "webstore_last_updated": null,
      "id": "fc577d34-e686-46c6-b3a6-a07531b4cba6",
      "size": null,
      "state": "active",
      "resource_locator_function": "information",
      "hash": "",
      "description": "Overview of the NASA GCMD Keywords.",
      "format": "HTML",
      "tracking_summary": {
        "total": 163,
        "recent": 14
      },
      "mimetype_inner": null,
      "url_type": null,
      "resource_locator_protocol": "HTTP",
      "mimetype": null,
      "cache_url": null,
      "name": "NASA GCMD Keyword Community Page",
      "created": "2016-10-03T22:14:34.212718",
      "url": "http://gcmd.gsfc.nasa.gov/learn/keywords.html",
      "webstore_url": null,
      "last_modified": null,
      "position": 9,
      "revision_id": "5ec3b6be-d505-43e9-ae8a-9d7b6716f5a8",
      "resource_type": null
    },
    {
      "cache_last_updated": null,
      "package_id": "bcff92d0-b503-4d02-a119-5aabc1efcf58",
      "webstore_last_updated": null,
      "id": "c5d2e199-e680-412b-8943-30cdc678e538",
      "size": null,
      "state": "active",
      "resource_locator_function": "information",
      "hash": "",
      "description": "Overview of the NASA GCMD Keywords.",
      "format": "HTML",
      "tracking_summary": {
        "total": 163,
        "recent": 14
      },
      "mimetype_inner": null,
      "url_type": null,
      "resource_locator_protocol": "HTTP",
      "mimetype": null,
      "cache_url": null,
      "name": "NASA GCMD Keyword Community Page",
      "created": "2016-10-03T22:14:34.212725",
      "url": "http://gcmd.gsfc.nasa.gov/learn/keywords.html",
      "webstore_url": null,
      "last_modified": null,
      "position": 10,
      "revision_id": "5ec3b6be-d505-43e9-ae8a-9d7b6716f5a8",
      "resource_type": null
    },
    {
      "cache_last_updated": null,
      "package_id": "bcff92d0-b503-4d02-a119-5aabc1efcf58",
      "webstore_last_updated": null,
      "id": "93ddfca2-fc27-4678-b1b5-a8732399bbc3",
      "size": null,
      "state": "active",
      "resource_locator_function": "information",
      "hash": "",
      "description": "Overview of the NASA GCMD Keywords.",
      "format": "HTML",
      "tracking_summary": {
        "total": 163,
        "recent": 14
      },
      "mimetype_inner": null,
      "url_type": null,
      "resource_locator_protocol": "HTTP",
      "mimetype": null,
      "cache_url": null,
      "name": "NASA GCMD Keyword Community Page",
      "created": "2016-10-03T22:14:34.212732",
      "url": "http://gcmd.gsfc.nasa.gov/learn/keywords.html",
      "webstore_url": null,
      "last_modified": null,
      "position": 11,
      "revision_id": "5ec3b6be-d505-43e9-ae8a-9d7b6716f5a8",
      "resource_type": null
    },
    {
      "cache_last_updated": null,
      "package_id": "bcff92d0-b503-4d02-a119-5aabc1efcf58",
      "webstore_last_updated": null,
      "id": "dc554fac-60e6-48e6-8d9e-f62538beddcf",
      "size": null,
      "state": "active",
      "resource_locator_function": "information",
      "hash": "",
      "description": "Overview of the NASA GCMD Keywords.",
      "format": "HTML",
      "tracking_summary": {
        "total": 163,
        "recent": 14
      },
      "mimetype_inner": null,
      "url_type": null,
      "resource_locator_protocol": "HTTP",
      "mimetype": null,
      "cache_url": null,
      "name": "NASA GCMD Keyword Community Page",
      "created": "2016-10-03T22:14:34.212739",
      "url": "http://gcmd.gsfc.nasa.gov/learn/keywords.html",
      "webstore_url": null,
      "last_modified": null,
      "position": 12,
      "revision_id": "5ec3b6be-d505-43e9-ae8a-9d7b6716f5a8",
      "resource_type": null
    }
  ],
  "num_resources": 13,
  "tags": [

  ],
  "tracking_summary": {
    "total": 2,
    "recent": 1
  },
  "groups": [

  ],
  "license_id": null,
  "relationships_as_subject": [

  ],
  "organization": {
    "description": "",
    "created": "2013-03-14T03:44:40.434269",
    "title": "National Oceanic and Atmospheric Administration, Department of Commerce",
    "name": "noaa-gov",
    "is_organization": true,
    "state": "active",
    "image_url": "https://fortress.wa.gov/dfw/score/score/images/noaa_logo.png",
    "revision_id": "c6d43080-22e1-405e-a83d-f2a512d9e867",
    "type": "organization",
    "id": "e811f0b4-451f-4896-9e8f-fc6802837819",
    "approval_status": "approved"
  },
  "name": "temperature-profiles-from-xbt-casts-from-the-oceanus-as-part-of-the-marine-resources-monitoring7f79b",
  "isopen": false,
  "url": null,
  "notes": "Temperature profiles were collected from XBT casts from the OCEANUS from 29 May 1981 to 30 May 1981. Data were collected by the National Marine Fisheries Service (NMFS) as part of the Marine Resources Monitoring, Assessment and Prediction (MARMAP) project. Data were processed by NODC to the NODC standard Universal Bathythermograph Output (UBT) format. Full format description is available from NODC at www.nodc.noaa.gov/General/NODC-Archive/bt.html.\n\nThe UBT format contains temperature-depth profile data obtained using expendable bathythermograph (XBT) instruments. Cruise information, position, date and time were reported for each observation. The data records are comprised of pairs of temperature-depth values. The XBT data files contain temperature values at non-uniform depths. These depths were recorded at the minimum number of points (\"inflection points\") required to accurately define the temperature curve. Standard XBTs can obtain profiles to depths of either 450 or 760 m. Special instruments permitted measurements to be obtained to 1830 m.",
  "owner_org": "e811f0b4-451f-4896-9e8f-fc6802837819",
  "extras": [
    {
      "key": "bbox-east-long",
      "value": "-69.984722"
    },
    {
      "key": "resource-type",
      "value": "dataset"
    },
    {
      "key": "bbox-north-lat",
      "value": "41.1525"
    },
    {
      "key": "coupled-resource",
      "value": "[]"
    },
    {
      "key": "graphic-preview-type",
      "value": "PNG"
    },
    {
      "key": "guid",
      "value": "gov.noaa.nodc:8100587"
    },
    {
      "key": "graphic-preview-file",
      "value": "https://data.nodc.noaa.gov/cgi-bin/gfx?id=gov.noaa.nodc:8100587"
    },
    {
      "key": "metadata-language",
      "value": "eng"
    },
    {
      "key": "spatial-reference-system",
      "value": ""
    },
    {
      "key": "spatial_harvester",
      "value": true
    },
    {
      "key": "spatial",
      "value": "{\"type\": \"Polygon\", \"coordinates\": [[[-71.000556, 39.518889], [-69.984722, 39.518889], [-69.984722, 41.1525], [-71.000556, 41.1525], [-71.000556, 39.518889]]]}"
    },
    {
      "key": "progress",
      "value": "completed"
    },
    {
      "key": "access_constraints",
      "value": "[\"Cite as: US DOC; NOAA; NMFS; Northeast Fisheries Science Center; Narragansett Laboratory (2013). Temperature profiles from XBT casts from the OCEANUS as part of the Marine Resources Monitoring, Assessment and Prediction (MARMAP) project from 1981-05-29 to 1981-05-30 (NODC Accession 8100587). Version 1.2. National Oceanographic Data Center, NOAA. Dataset. [access date]\", \"NOAA and NCEI cannot provide any warranty as to the accuracy, reliability, or completeness of furnished data. Users assume responsibility to determine the usability of these data. The user is responsible for the results of any application of this data for other than its intended purpose.\"]"
    },
    {
      "key": "temporal-extent-begin",
      "value": "1981-05-29"
    },
    {
      "key": "contact-email",
      "value": "NCEI.Info@noaa.gov"
    },
    {
      "key": "bbox-west-long",
      "value": "-71.000556"
    },
    {
      "key": "metadata-date",
      "value": "2016-09-20T19:31:58"
    },
    {
      "key": "dataset-reference-date",
      "value": "[{\"type\": \"publication\", \"value\": \"2013-03-19\"}]"
    },
    {
      "key": "graphic-preview-description",
      "value": "Preview graphic"
    },
    {
      "key": "frequency-of-update",
      "value": "asNeeded"
    },
    {
      "key": "licence",
      "value": "[\"accessLevel: Public\"]"
    },
    {
      "key": "metadata_type",
      "value": "geospatial"
    },
    {
      "key": "responsible-party",
      "value": "[{\"name\": \"DOC/NOAA/NESDIS/NCEI > National Centers for Environmental Information, NESDIS, NOAA, U.S. Department of Commerce\", \"roles\": [\"pointOfContact\"]}]"
    },
    {
      "key": "temporal-extent-end",
      "value": "1981-05-30"
    },
    {
      "key": "spatial-data-service-type",
      "value": ""
    },
    {
      "key": "bbox-south-lat",
      "value": "39.518889"
    },
    {
      "key": "tags",
      "value": "ocean temperature, marmap, noaa, doc/noaa/nesdis/ncei, expendable bathythermographs, national oceanographic data center, nesdis, noaa, u.s. department of commerce, earth science, oceanography, profilers/sounders, in situ/laboratory instruments, government agencies-u.s. federal agencies, atlantic ocean, national centers for environmental information, nesdis, noaa, u.s. department of commerce, north atlantic ocean, marine resources, monitoring, assessment and prediction, oceans, doc/noaa/nmfs/nefsc, m - o, bathythermographs, water temperature, doc/noaa/nesdis/nodc, http://www.nefsc.noaa.gov/, northeast fisheries science center, national marine fisheries service, noaa, u.s. department of commerce, doc, ocean, xbt"
    },
    {
      "key": "harvest_object_id",
      "value": "3ac8e8e7-6850-4601-9fef-5d641592cee9"
    },
    {
      "key": "harvest_source_id",
      "value": "2aed8e29-fc5b-4cde-aa66-fb1118fd705e"
    },
    {
      "key": "harvest_source_title",
      "value": "NOAA CSW Harvest Source"
    }
  ],
  "title": "Temperature profiles from XBT casts from the OCEANUS as part of the Marine Resources Monitoring, Assessment and Prediction (MARMAP) project from 1981-05-29 to 1981-05-30 (NODC Accession 8100587)",
  "revision_id": "5ec3b6be-d505-43e9-ae8a-9d7b6716f5a8"
}