{
  "license_title": null,
  "maintainer": null,
  "relationships_as_object": [

  ],
  "private": false,
  "maintainer_email": null,
  "num_tags": 0,
  "id": "fe4eefbf-4a07-40b2-928f-6b23c9386962",
  "metadata_created": "2015-09-27T00:41:23.765595",
  "metadata_modified": "2016-09-13T01:20:07.393285",
  "author": null,
  "author_email": null,
  "state": "active",
  "version": null,
  "creator_user_id": "47303a9e-1187-4290-85a3-1fc02dc49e4a",
  "type": "dataset",
  "resources": [
    {
      "cache_last_updated": null,
      "package_id": "fe4eefbf-4a07-40b2-928f-6b23c9386962",
      "webstore_last_updated": null,
      "id": "b38b8245-19f1-4a6f-8f7a-bfbd1c4f5af6",
      "size": null,
      "state": "active",
      "resource_locator_function": "download",
      "hash": "",
      "description": "Navigate directly to the URL for data access and direct download.",
      "format": "NetCDF",
      "tracking_summary": {
        "total": 0,
        "recent": 0
      },
      "mimetype_inner": null,
      "url_type": null,
      "resource_locator_protocol": "HTTP",
      "mimetype": null,
      "cache_url": null,
      "name": "HTTP",
      "created": "2016-09-12T21:20:07.864907",
      "url": "https://data.nodc.noaa.gov/ndbc/tao-ctd/2010/WE-10-01/",
      "webstore_url": null,
      "last_modified": null,
      "position": 0,
      "revision_id": "d5c35d24-528c-41e9-b55b-17abff98ba1d",
      "resource_type": null
    },
    {
      "cache_last_updated": null,
      "package_id": "fe4eefbf-4a07-40b2-928f-6b23c9386962",
      "webstore_last_updated": null,
      "id": "931f2ab6-aefb-487c-9be3-edf651ddb196",
      "size": null,
      "state": "active",
      "resource_locator_function": "information",
      "hash": "",
      "description": "Navigate directly to the URL for a descriptive web page with download links.",
      "format": "NetCDF",
      "tracking_summary": {
        "total": 0,
        "recent": 0
      },
      "mimetype_inner": null,
      "url_type": null,
      "resource_locator_protocol": "HTTP",
      "mimetype": null,
      "cache_url": null,
      "name": "Descriptive Information",
      "created": "2016-09-12T21:20:07.864957",
      "url": "https://accession.nodc.noaa.gov/0120364",
      "webstore_url": null,
      "last_modified": null,
      "position": 1,
      "revision_id": "d5c35d24-528c-41e9-b55b-17abff98ba1d",
      "resource_type": null
    },
    {
      "cache_last_updated": null,
      "package_id": "fe4eefbf-4a07-40b2-928f-6b23c9386962",
      "webstore_last_updated": null,
      "id": "31efe915-c750-4b76-b3af-13d7390760c1",
      "size": null,
      "state": "active",
      "resource_locator_function": "download",
      "hash": "",
      "description": "These data are available through a variety of services via a THREDDS (Thematic Real-time Environmental Distributed Data Services) Data Server (TDS). Depending on the dataset, the TDS can provide WMS, WCS, DAP, HTTP, and other data access and metadata services as well. For more information on the TDS, see http://www.unidata.ucar.edu/software/thredds/current/tds/.",
      "format": "NetCDF",
      "tracking_summary": {
        "total": 0,
        "recent": 0
      },
      "mimetype_inner": null,
      "url_type": null,
      "resource_locator_protocol": "THREDDS",
      "mimetype": null,
      "cache_url": null,
      "name": "THREDDS",
      "created": "2016-09-12T21:20:07.864971",
      "url": "https://data.nodc.noaa.gov/thredds/catalog/ndbc/tao-ctd/2010/WE-10-01/",
      "webstore_url": null,
      "last_modified": null,
      "position": 2,
      "revision_id": "d5c35d24-528c-41e9-b55b-17abff98ba1d",
      "resource_type": null
    },
    {
      "cache_last_updated": null,
      "package_id": "fe4eefbf-4a07-40b2-928f-6b23c9386962",
      "webstore_last_updated": null,
      "id": "ab183764-07b4-4959-94b1-3bca08e41f18",
      "size": null,
      "state": "active",
      "resource_locator_function": "download",
      "hash": "",
      "description": "These data are available through the Data Access Protocol (DAP) via an OPeNDAP Hyrax server. For a listing of OPeNDAP clients which may be used to access OPeNDAP-enabled data sets, please see the OPeNDAP website at http://opendap.org/.",
      "format": "NetCDF",
      "tracking_summary": {
        "total": 0,
        "recent": 0
      },
      "mimetype_inner": null,
      "url_type": null,
      "resource_locator_protocol": "DAP",
      "mimetype": null,
      "cache_url": null,
      "name": "OPeNDAP",
      "created": "2016-09-12T21:20:07.864983",
      "url": "https://data.nodc.noaa.gov/opendap/ndbc/tao-ctd/2010/WE-10-01/",
      "webstore_url": null,
      "last_modified": null,
      "position": 3,
      "revision_id": "d5c35d24-528c-41e9-b55b-17abff98ba1d",
      "resource_type": null
    },
    {
      "cache_last_updated": null,
      "package_id": "fe4eefbf-4a07-40b2-928f-6b23c9386962",
      "webstore_last_updated": null,
      "id": "97f1ffbc-e53a-448e-aca1-a72155117469",
      "size": null,
      "state": "active",
      "resource_locator_function": "information",
      "hash": "",
      "description": "Navigate directly to the URL for a descriptive web page with download links.",
      "format": "NetCDF",
      "tracking_summary": {
        "total": 0,
        "recent": 0
      },
      "mimetype_inner": null,
      "url_type": null,
      "resource_locator_protocol": "HTTP",
      "mimetype": null,
      "cache_url": null,
      "name": "Descriptive Information",
      "created": "2016-09-12T21:20:07.864994",
      "url": "https://accession.nodc.noaa.gov/oas/120364",
      "webstore_url": null,
      "last_modified": null,
      "position": 4,
      "revision_id": "d5c35d24-528c-41e9-b55b-17abff98ba1d",
      "resource_type": null
    },
    {
      "cache_last_updated": null,
      "package_id": "fe4eefbf-4a07-40b2-928f-6b23c9386962",
      "webstore_last_updated": null,
      "id": "ce779f12-3f19-488c-8fa9-b7c964d90193",
      "size": null,
      "state": "active",
      "resource_locator_function": "download",
      "hash": "",
      "description": "Navigate directly to the URL for data access and direct download.",
      "format": "NetCDF",
      "tracking_summary": {
        "total": 0,
        "recent": 0
      },
      "mimetype_inner": null,
      "url_type": null,
      "resource_locator_protocol": "HTTP",
      "mimetype": null,
      "cache_url": null,
      "name": "HTTP",
      "created": "2016-09-12T21:20:07.865005",
      "url": "https://accession.nodc.noaa.gov/download/120364",
      "webstore_url": null,
      "last_modified": null,
      "position": 5,
      "revision_id": "d5c35d24-528c-41e9-b55b-17abff98ba1d",
      "resource_type": null
    },
    {
      "cache_last_updated": null,
      "package_id": "fe4eefbf-4a07-40b2-928f-6b23c9386962",
      "webstore_last_updated": null,
      "id": "d1baaa5a-a524-4522-801d-e1f661dac4dd",
      "size": null,
      "state": "active",
      "resource_locator_function": "download",
      "hash": "",
      "description": "These data are available through the File Transfer Protocol (FTP). You may use any FTP client to download these data.",
      "format": "NetCDF",
      "tracking_summary": {
        "total": 0,
        "recent": 0
      },
      "mimetype_inner": null,
      "url_type": null,
      "resource_locator_protocol": "FTP",
      "mimetype": null,
      "cache_url": null,
      "name": "FTP",
      "created": "2016-09-12T21:20:07.865017",
      "url": "ftp://ftp.nodc.noaa.gov/nodc/archive/arc0067/0120364/",
      "webstore_url": null,
      "last_modified": null,
      "position": 6,
      "revision_id": "d5c35d24-528c-41e9-b55b-17abff98ba1d",
      "resource_type": null
    },
    {
      "cache_last_updated": null,
      "package_id": "fe4eefbf-4a07-40b2-928f-6b23c9386962",
      "webstore_last_updated": null,
      "id": "209afc15-48cb-40e7-9ab2-5d72e4ffe16a",
      "size": null,
      "state": "active",
      "resource_locator_function": "information",
      "hash": "",
      "description": "Main NCEI website providing links to access data and data services.",
      "format": "",
      "tracking_summary": {
        "total": 51,
        "recent": 8
      },
      "mimetype_inner": null,
      "url_type": null,
      "resource_locator_protocol": "HTTP",
      "mimetype": null,
      "cache_url": null,
      "name": "NOAA National Centers for Environmental Information website",
      "created": "2016-09-12T21:20:07.865028",
      "url": "https://www.ncei.noaa.gov/",
      "webstore_url": null,
      "last_modified": null,
      "position": 7,
      "revision_id": "d5c35d24-528c-41e9-b55b-17abff98ba1d",
      "resource_type": null
    },
    {
      "cache_last_updated": null,
      "package_id": "fe4eefbf-4a07-40b2-928f-6b23c9386962",
      "webstore_last_updated": null,
      "id": "80cf3fa3-87f6-418d-a574-747a4407a806",
      "size": null,
      "state": "active",
      "resource_locator_function": "information",
      "hash": "",
      "description": "Main NODC website providing links to access data and data services.",
      "format": "",
      "tracking_summary": {
        "total": 7,
        "recent": 1
      },
      "mimetype_inner": null,
      "url_type": null,
      "resource_locator_protocol": "HTTP",
      "mimetype": null,
      "cache_url": null,
      "name": "NOAA National Oceanographic Data Center website",
      "created": "2016-09-12T21:20:07.865039",
      "url": "https://www.nodc.noaa.gov/",
      "webstore_url": null,
      "last_modified": null,
      "position": 8,
      "revision_id": "d5c35d24-528c-41e9-b55b-17abff98ba1d",
      "resource_type": null
    },
    {
      "cache_last_updated": null,
      "package_id": "fe4eefbf-4a07-40b2-928f-6b23c9386962",
      "webstore_last_updated": null,
      "id": "a071f126-9fb4-451a-87da-711b882c9fa4",
      "size": null,
      "state": "active",
      "resource_locator_function": "information",
      "hash": "",
      "description": "Institution web page",
      "format": "",
      "tracking_summary": {
        "total": 5,
        "recent": 2
      },
      "mimetype_inner": null,
      "url_type": null,
      "resource_locator_protocol": "HTTP",
      "mimetype": null,
      "cache_url": null,
      "name": "US DOC; NOAA; NWS; National Data Buoy Center (NDBC) website",
      "created": "2016-09-12T21:20:07.865051",
      "url": "http://www.ndbc.noaa.gov/",
      "webstore_url": null,
      "last_modified": null,
      "position": 9,
      "revision_id": "d5c35d24-528c-41e9-b55b-17abff98ba1d",
      "resource_type": null
    },
    {
      "cache_last_updated": null,
      "package_id": "fe4eefbf-4a07-40b2-928f-6b23c9386962",
      "webstore_last_updated": null,
      "id": "d947ba61-b327-401b-be22-8e92c92194ea",
      "size": null,
      "state": "active",
      "resource_locator_function": "information",
      "hash": "",
      "description": "Institution web page",
      "format": "",
      "tracking_summary": {
        "total": 5,
        "recent": 2
      },
      "mimetype_inner": null,
      "url_type": null,
      "resource_locator_protocol": "HTTP",
      "mimetype": null,
      "cache_url": null,
      "name": "US DOC; NOAA; NWS; National Data Buoy Center (NDBC) website",
      "created": "2016-09-12T21:20:07.865062",
      "url": "http://www.ndbc.noaa.gov/",
      "webstore_url": null,
      "last_modified": null,
      "position": 10,
      "revision_id": "d5c35d24-528c-41e9-b55b-17abff98ba1d",
      "resource_type": null
    },
    {
      "cache_last_updated": null,
      "package_id": "fe4eefbf-4a07-40b2-928f-6b23c9386962",
      "webstore_last_updated": null,
      "id": "6f467934-c5ae-432f-992a-e76f41b8fba7",
      "size": null,
      "state": "active",
      "resource_locator_function": "information",
      "hash": "",
      "description": "Main NCEI website providing links to access data and data services.",
      "format": "",
      "tracking_summary": {
        "total": 51,
        "recent": 8
      },
      "mimetype_inner": null,
      "url_type": null,
      "resource_locator_protocol": "HTTP",
      "mimetype": null,
      "cache_url": null,
      "name": "NOAA National Centers for Environmental Information website",
      "created": "2016-09-12T21:20:07.865073",
      "url": "https://www.ncei.noaa.gov/",
      "webstore_url": null,
      "last_modified": null,
      "position": 11,
      "revision_id": "d5c35d24-528c-41e9-b55b-17abff98ba1d",
      "resource_type": null
    },
    {
      "cache_last_updated": null,
      "package_id": "fe4eefbf-4a07-40b2-928f-6b23c9386962",
      "webstore_last_updated": null,
      "id": "c9bc1288-179e-40e3-9497-508475bb3954",
      "size": null,
      "state": "active",
      "resource_locator_function": "information",
      "hash": "",
      "description": "Overview of the NASA GCMD Keywords.",
      "format": "HTML",
      "tracking_summary": {
        "total": 163,
        "recent": 14
      },
      "mimetype_inner": null,
      "url_type": null,
      "resource_locator_protocol": "HTTP",
      "mimetype": null,
      "cache_url": null,
      "name": "NASA GCMD Keyword Community Page",
      "created": "2016-09-12T21:20:07.865084",
      "url": "http://gcmd.gsfc.nasa.gov/learn/keywords.html",
      "webstore_url": null,
      "last_modified": null,
      "position": 12,
      "revision_id": "d5c35d24-528c-41e9-b55b-17abff98ba1d",
      "resource_type": null
    },
    {
      "cache_last_updated": null,
      "package_id": "fe4eefbf-4a07-40b2-928f-6b23c9386962",
      "webstore_last_updated": null,
      "id": "ad7ecd84-12d4-4af8-bf54-c2b98f05929e",
      "size": null,
      "state": "active",
      "resource_locator_function": "information",
      "hash": "",
      "description": "Overview of the NASA GCMD Keywords.",
      "format": "HTML",
      "tracking_summary": {
        "total": 163,
        "recent": 14
      },
      "mimetype_inner": null,
      "url_type": null,
      "resource_locator_protocol": "HTTP",
      "mimetype": null,
      "cache_url": null,
      "name": "NASA GCMD Keyword Community Page",
      "created": "2016-09-12T21:20:07.865095",
      "url": "http://gcmd.gsfc.nasa.gov/learn/keywords.html",
      "webstore_url": null,
      "last_modified": null,
      "position": 13,
      "revision_id": "d5c35d24-528c-41e9-b55b-17abff98ba1d",
      "resource_type": null
    },
    {
      "cache_last_updated": null,
      "package_id": "fe4eefbf-4a07-40b2-928f-6b23c9386962",
      "webstore_last_updated": null,
      "id": "ea2f0e6b-e18a-41c8-9462-ed3850dd4946",
      "size": null,
      "state": "active",
      "resource_locator_function": "information",
      "hash": "",
      "description": "Overview of the NASA GCMD Keywords.",
      "format": "HTML",
      "tracking_summary": {
        "total": 163,
        "recent": 14
      },
      "mimetype_inner": null,
      "url_type": null,
      "resource_locator_protocol": "HTTP",
      "mimetype": null,
      "cache_url": null,
      "name": "NASA GCMD Keyword Community Page",
      "created": "2016-09-12T21:20:07.865105",
      "url": "http://gcmd.gsfc.nasa.gov/learn/keywords.html",
      "webstore_url": null,
      "last_modified": null,
      "position": 14,
      "revision_id": "d5c35d24-528c-41e9-b55b-17abff98ba1d",
      "resource_type": null
    },
    {
      "cache_last_updated": null,
      "package_id": "fe4eefbf-4a07-40b2-928f-6b23c9386962",
      "webstore_last_updated": null,
      "id": "b0137327-3a40-4894-acab-b0aa764bc94a",
      "size": null,
      "state": "active",
      "resource_locator_function": "information",
      "hash": "",
      "description": "Overview of the NASA GCMD Keywords.",
      "format": "HTML",
      "tracking_summary": {
        "total": 163,
        "recent": 14
      },
      "mimetype_inner": null,
      "url_type": null,
      "resource_locator_protocol": "HTTP",
      "mimetype": null,
      "cache_url": null,
      "name": "NASA GCMD Keyword Community Page",
      "created": "2016-09-12T21:20:07.865117",
      "url": "http://gcmd.gsfc.nasa.gov/learn/keywords.html",
      "webstore_url": null,
      "last_modified": null,
      "position": 15,
      "revision_id": "d5c35d24-528c-41e9-b55b-17abff98ba1d",
      "resource_type": null
    },
    {
      "cache_last_updated": null,
      "package_id": "fe4eefbf-4a07-40b2-928f-6b23c9386962",
      "webstore_last_updated": null,
      "id": "7a774d5b-0974-48b2-b142-4ecb5dd0a83b",
      "size": null,
      "state": "active",
      "resource_locator_function": "information",
      "hash": "",
      "description": "Overview of the NASA GCMD Keywords.",
      "format": "HTML",
      "tracking_summary": {
        "total": 163,
        "recent": 14
      },
      "mimetype_inner": null,
      "url_type": null,
      "resource_locator_protocol": "HTTP",
      "mimetype": null,
      "cache_url": null,
      "name": "NASA GCMD Keyword Community Page",
      "created": "2016-09-12T21:20:07.865128",
      "url": "http://gcmd.gsfc.nasa.gov/learn/keywords.html",
      "webstore_url": null,
      "last_modified": null,
      "position": 16,
      "revision_id": "d5c35d24-528c-41e9-b55b-17abff98ba1d",
      "resource_type": null
    },
    {
      "cache_last_updated": null,
      "package_id": "fe4eefbf-4a07-40b2-928f-6b23c9386962",
      "webstore_last_updated": null,
      "id": "48579f0a-808d-4dfb-a4bd-945221ac820b",
      "size": null,
      "state": "active",
      "resource_locator_function": "download",
      "hash": "",
      "description": "data in ASCII text format",
      "format": "",
      "tracking_summary": {
        "total": 0,
        "recent": 0
      },
      "mimetype_inner": null,
      "url_type": null,
      "resource_locator_protocol": "HTTP",
      "mimetype": null,
      "cache_url": null,
      "name": "NODC Accession 0100229",
      "created": "2016-09-12T21:20:07.865138",
      "url": "http://accession.nodc.noaa.gov/0100229",
      "webstore_url": null,
      "last_modified": null,
      "position": 17,
      "revision_id": "d5c35d24-528c-41e9-b55b-17abff98ba1d",
      "resource_type": null
    },
    {
      "cache_last_updated": null,
      "package_id": "fe4eefbf-4a07-40b2-928f-6b23c9386962",
      "webstore_last_updated": null,
      "id": "8abda986-710c-41e1-9f08-c110e8c6c36a",
      "size": null,
      "state": "active",
      "resource_locator_function": "information",
      "hash": "",
      "description": "PDF document",
      "format": "PDF",
      "tracking_summary": {
        "total": 1,
        "recent": 1
      },
      "mimetype_inner": null,
      "url_type": null,
      "resource_locator_protocol": "HTTP",
      "mimetype": null,
      "cache_url": null,
      "name": "The TAO Shipboard CTD Program Under the National Data Buoy Center",
      "created": "2016-09-12T21:20:07.865150",
      "url": "http://accession.nodc.noaa.gov/0118678/data/0-data/Boyd_et_al_NDBC_TAO_CTD_Program.pdf",
      "webstore_url": null,
      "last_modified": null,
      "position": 18,
      "revision_id": "d5c35d24-528c-41e9-b55b-17abff98ba1d",
      "resource_type": null
    },
    {
      "cache_last_updated": null,
      "package_id": "fe4eefbf-4a07-40b2-928f-6b23c9386962",
      "webstore_last_updated": null,
      "id": "a8939500-370b-4ea5-bdba-e7cbb84be5a3",
      "size": null,
      "state": "active",
      "resource_locator_function": "information",
      "hash": "",
      "description": "Institution web page",
      "format": "",
      "tracking_summary": {
        "total": 5,
        "recent": 2
      },
      "mimetype_inner": null,
      "url_type": null,
      "resource_locator_protocol": "HTTP",
      "mimetype": null,
      "cache_url": null,
      "name": "US DOC; NOAA; NWS; National Data Buoy Center (NDBC) website",
      "created": "2016-09-12T21:20:07.865161",
      "url": "http://www.ndbc.noaa.gov/",
      "webstore_url": null,
      "last_modified": null,
      "position": 19,
      "revision_id": "d5c35d24-528c-41e9-b55b-17abff98ba1d",
      "resource_type": null
    },
    {
      "cache_last_updated": null,
      "package_id": "fe4eefbf-4a07-40b2-928f-6b23c9386962",
      "webstore_last_updated": null,
      "id": "503b3df6-7881-4735-a351-571d2c0af32a",
      "size": null,
      "state": "active",
      "resource_locator_function": "information",
      "hash": "",
      "description": "Institution web page",
      "format": "",
      "tracking_summary": {
        "total": 5,
        "recent": 2
      },
      "mimetype_inner": null,
      "url_type": null,
      "resource_locator_protocol": "HTTP",
      "mimetype": null,
      "cache_url": null,
      "name": "US DOC; NOAA; NWS; National Data Buoy Center (NDBC) website",
      "created": "2016-09-12T21:20:07.865172",
      "url": "http://www.ndbc.noaa.gov/",
      "webstore_url": null,
      "last_modified": null,
      "position": 20,
      "revision_id": "d5c35d24-528c-41e9-b55b-17abff98ba1d",
      "resource_type": null
    }
  ],
  "num_resources": 21,
  "tags": [

  ],
  "tracking_summary": {
    "total": 1,
    "recent": 0
  },
  "groups": [

  ],
  "license_id": null,
  "relationships_as_subject": [

  ],
  "organization": {
    "description": "",
    "created": "2013-03-14T03:44:40.434269",
    "title": "National Oceanic and Atmospheric Administration, Department of Commerce",
    "name": "noaa-gov",
    "is_organization": true,
    "state": "active",
    "image_url": "https://fortress.wa.gov/dfw/score/score/images/noaa_logo.png",
    "revision_id": "c6d43080-22e1-405e-a83d-f2a512d9e867",
    "type": "organization",
    "id": "e811f0b4-451f-4896-9e8f-fc6802837819",
    "approval_status": "approved"
  },
  "name": "physical-profile-data-collected-from-ctd-casts-from-the-wecoma-in-the-equatorial-pacific-during4de64",
  "isopen": false,
  "url": null,
  "notes": "As part of the Tropical Atmosphere Ocean (TAO) Program, the National Data Buoy Center (NDBC) was responsible for the at-sea collection, quality control and processing, and delivery of these CTD data in netCDF files to the National Oceanographic Data Center (NODC). NDBC collected these CTD data during a cruise to service the TAO array of moorings.",
  "owner_org": "e811f0b4-451f-4896-9e8f-fc6802837819",
  "extras": [
    {
      "key": "bbox-east-long",
      "value": "-94.9423"
    },
    {
      "key": "resource-type",
      "value": "dataset"
    },
    {
      "key": "bbox-north-lat",
      "value": "8.0342"
    },
    {
      "key": "coupled-resource",
      "value": "[]"
    },
    {
      "key": "graphic-preview-type",
      "value": "PNG"
    },
    {
      "key": "guid",
      "value": "gov.noaa.nodc:0120364"
    },
    {
      "key": "graphic-preview-file",
      "value": "https://data.nodc.noaa.gov/cgi-bin/gfx?id=gov.noaa.nodc:0120364"
    },
    {
      "key": "metadata-language",
      "value": "eng"
    },
    {
      "key": "spatial-reference-system",
      "value": ""
    },
    {
      "key": "spatial_harvester",
      "value": true
    },
    {
      "key": "spatial",
      "value": "{\"type\": \"Polygon\", \"coordinates\": [[[-110.1735, -7.9717], [-94.9423, -7.9717], [-94.9423, 8.0342], [-110.1735, 8.0342], [-110.1735, -7.9717]]]}"
    },
    {
      "key": "progress",
      "value": "completed"
    },
    {
      "key": "access_constraints",
      "value": "[\"Cite as: Petraitis, D. and US DOC; NOAA; NWS; National Data Buoy Center (2014). Physical profile data collected from CTD casts from the WECOMA in the Equatorial Pacific during cruise WE-10-01 to service the Tropical Atmosphere Ocean (TAO) array from 2010-03-11 to 2010-03-27 (NODC Accession 0120364). Version 1.1. National Oceanographic Data Center, NOAA. Dataset. [access date]\", \"NOAA and NCEI cannot provide any warranty as to the accuracy, reliability, or completeness of furnished data. Users assume responsibility to determine the usability of these data. The user is responsible for the results of any application of this data for other than its intended purpose.\"]"
    },
    {
      "key": "temporal-extent-begin",
      "value": "2010-03-11"
    },
    {
      "key": "contact-email",
      "value": "NCEI.Info@noaa.gov"
    },
    {
      "key": "bbox-west-long",
      "value": "-110.1735"
    },
    {
      "key": "metadata-date",
      "value": "2016-08-24T03:53:12"
    },
    {
      "key": "dataset-reference-date",
      "value": "[{\"type\": \"publication\", \"value\": \"2014-07-15\"}]"
    },
    {
      "key": "graphic-preview-description",
      "value": "Preview graphic"
    },
    {
      "key": "frequency-of-update",
      "value": "asNeeded"
    },
    {
      "key": "licence",
      "value": "[\"accessLevel: Public\"]"
    },
    {
      "key": "metadata_type",
      "value": "geospatial"
    },
    {
      "key": "responsible-party",
      "value": "[{\"name\": \"DOC/NOAA/NESDIS/NCEI > National Centers for Environmental Information, NESDIS, NOAA, U.S. Department of Commerce\", \"roles\": [\"pointOfContact\"]}]"
    },
    {
      "key": "temporal-extent-end",
      "value": "2010-03-27"
    },
    {
      "key": "spatial-data-service-type",
      "value": ""
    },
    {
      "key": "bbox-south-lat",
      "value": "-7.9717"
    },
    {
      "key": "tags",
      "value": "ocean temperature, atmosphere, ocean waves, sea_water_pressure_due_to_sea_water, http://www.ndbc.noaa.gov/, conductivity, temperature, depth, south pacific ocean, seabird/sbe 4c, noaa, ocean optics, doc/noaa/nesdis/ncei, ocean, national oceanographic data center, nesdis, noaa, u.s. department of commerce, cloud properties, earth science, pacific ocean, oceanography, atmospheric pressure, in situ/laboratory instruments, wind speed/wind direction, water temperature, atmospheric temperature, national data buoy center, national weather service, noaa, u.s. department of commerce, national centers for environmental information, nesdis, noaa, u.s. department of commerce, doc/noaa/nws/ndbc, oceans, sea_water_practical_salinity, surface winds, swells, seabird/sbe 3t, government agencies-u.s. federal agencies, doc/noaa/nesdis/nodc, salinity/density, atmospheric winds, clouds, cloud frequency, surface temperature, doc, air temperature, salinity, ctd, profilers/sounders, north pacific ocean, hydrostatic pressure, sea_water_temperature"
    },
    {
      "key": "harvest_object_id",
      "value": "d1f8797e-261f-4114-b4de-7d5d6fce92c1"
    },
    {
      "key": "harvest_source_id",
      "value": "2aed8e29-fc5b-4cde-aa66-fb1118fd705e"
    },
    {
      "key": "harvest_source_title",
      "value": "NOAA CSW Harvest Source"
    }
  ],
  "title": "Physical profile data collected from CTD casts from the WECOMA in the Equatorial Pacific during cruise WE-10-01 to service the Tropical Atmosphere Ocean (TAO) array from 2010-03-11 to 2010-03-27 (NODC Accession 0120364)",
  "revision_id": "bbe88ea8-aafe-4ed8-a603-ece1f90e681d"
}