{
  "license_title": "License not specified",
  "maintainer": "Richard Easterbrook",
  "relationships_as_object": [

  ],
  "private": false,
  "maintainer_email": "richard_easterbrook@fws.gov",
  "num_tags": 4,
  "id": "026e97a1-b6af-4bee-aa91-16ee5ea02346",
  "metadata_created": "2015-06-17T01:57:06.458688",
  "metadata_modified": "2016-07-27T23:02:14.131347",
  "author": null,
  "author_email": null,
  "state": "active",
  "version": null,
  "creator_user_id": "47303a9e-1187-4290-85a3-1fc02dc49e4a",
  "type": "dataset",
  "resources": [
    {
      "cache_last_updated": null,
      "package_id": "026e97a1-b6af-4bee-aa91-16ee5ea02346",
      "webstore_last_updated": null,
      "id": "57322a18-3839-48fa-8352-e97d0b440232",
      "size": null,
      "state": "active",
      "hash": "",
      "description": "",
      "format": "PDF",
      "tracking_summary": {
        "total": 0,
        "recent": 0
      },
      "last_modified": null,
      "url_type": null,
      "mimetype": "application/pdf",
      "cache_url": null,
      "name": "FWLB0577.PDF",
      "created": "2016-07-27T19:02:14.201871",
      "url": "https://ecos.fws.gov/ServCat/DownloadFile/49985?Reference=49457",
      "webstore_url": null,
      "mimetype_inner": null,
      "position": 0,
      "revision_id": "ad8f0549-a443-442c-8264-4c7da8aeabfb",
      "resource_type": null
    }
  ],
  "num_resources": 1,
  "tags": [
    {
      "vocabulary_id": null,
      "state": "active",
      "display_name": "caribou",
      "id": "54ba4032-9e0a-4ee2-bdb3-8291f21fd4ab",
      "name": "caribou"
    },
    {
      "vocabulary_id": null,
      "state": "active",
      "display_name": "distribution",
      "id": "db0c8d44-ddd4-44cb-af45-4e561ee6db48",
      "name": "distribution"
    },
    {
      "vocabulary_id": null,
      "state": "active",
      "display_name": "rangifer-tarandus",
      "id": "729fbe20-ee97-44d3-a554-35b1c3ba5d49",
      "name": "rangifer-tarandus"
    },
    {
      "vocabulary_id": null,
      "state": "active",
      "display_name": "reindeer",
      "id": "9ffb393b-aa52-4367-97a5-9a2bb70e8fd5",
      "name": "reindeer"
    }
  ],
  "tracking_summary": {
    "total": 2,
    "recent": 2
  },
  "groups": [

  ],
  "license_id": "notspecified",
  "relationships_as_subject": [

  ],
  "organization": {
    "description": "",
    "created": "2013-03-14T03:44:48.890979",
    "title": "US Fish and Wildlife Service, Department of the Interior",
    "name": "fws-gov",
    "is_organization": true,
    "state": "active",
    "image_url": "http://upload.wikimedia.org/wikipedia/commons/0/0c/US-FishAndWildlifeService-Logo.svg",
    "revision_id": "353573b3-02ba-4e95-a876-828e8972ac08",
    "type": "organization",
    "id": "4d7ad1cd-3641-420b-8116-e4082f49cd44",
    "approval_status": "approved"
  },
  "name": "reconnaissance-survey-reindeer-and-muskox-range-february-22-25-1972",
  "isopen": false,
  "url": null,
  "notes": "This report is on the reconnaissance survey on reindeer and muskox range on Nunivak Island in Alaska. Weather, species examined, prospects, results are included.",
  "owner_org": "4d7ad1cd-3641-420b-8116-e4082f49cd44",
  "extras": [
    {
      "key": "harvest_source_id",
      "value": "269d76fb-fa7e-49d2-a6bb-3a9e3f1bee70"
    },
    {
      "key": "issued",
      "value": "1972-01-01"
    },
    {
      "key": "resource-type",
      "value": "Dataset"
    },
    {
      "key": "references",
      "value": [
        "https://ecos.fws.gov/ServCat/Reference/Profile/49457"
      ]
    },
    {
      "key": "source_hash",
      "value": "d21f6ca1431411aacd615b79102a1f32559d7c8e"
    },
    {
      "key": "accessLevel",
      "value": "public"
    },
    {
      "key": "theme",
      "value": [
        "Unpublished Report"
      ]
    },
    {
      "key": "spatial",
      "value": "-167.852325,59.6325264,-159.136978,63.4883766"
    },
    {
      "key": "catalog_conformsTo",
      "value": "https://project-open-data.cio.gov/v1.1/schema"
    },
    {
      "key": "catalog_@context",
      "value": "https://project-open-data.cio.gov/v1.1/schema/catalog.jsonld"
    },
    {
      "key": "catalog_describedBy",
      "value": "https://project-open-data.cio.gov/v1.1/schema/catalog.json"
    },
    {
      "key": "harvest_source_title",
      "value": "fwsjson"
    },
    {
      "key": "source_schema_version",
      "value": "1.1"
    },
    {
      "key": "programCode",
      "value": [
        "010:094",
        "010:028"
      ]
    },
    {
      "key": "bureauCode",
      "value": [
        "010:18"
      ]
    },
    {
      "key": "landingPage",
      "value": "https://ecos.fws.gov/ServCat/Reference/Profile/49457"
    },
    {
      "key": "harvest_object_id",
      "value": "6f08439d-1bb8-4f92-8984-3f23aeec87ae"
    },
    {
      "key": "publisher",
      "value": "Fish and Wildlife Service"
    },
    {
      "key": "modified",
      "value": "1972-01-01"
    },
    {
      "key": "source_datajson_identifier",
      "value": true
    },
    {
      "key": "catalog_@id",
      "value": "C:\\Program Files (x86)\\FWS\\DataStore\\Application\\OpenData\\FWS_ServCat_v1_1.json"
    },
    {
      "key": "dataQuality",
      "value": true
    },
    {
      "key": "identifier",
      "value": "FWS_ServCat_49457"
    },
    {
      "key": "harvest_object_id",
      "value": "6f08439d-1bb8-4f92-8984-3f23aeec87ae"
    },
    {
      "key": "harvest_source_id",
      "value": "269d76fb-fa7e-49d2-a6bb-3a9e3f1bee70"
    },
    {
      "key": "harvest_source_title",
      "value": "fwsjson"
    }
  ],
  "title": "Reconnaissance survey, reindeer and muskox range, , February 22-25, 1972",
  "revision_id": "be9398ee-9c8e-40cb-91f8-fcd77bd75867"
}